docs/development.md
docs/usage.md
gpt_po_translator-2.0.1.dist-info/licenses/LICENSE
python_gpt_po/__init__.py
python_gpt_po/_version.py
python_gpt_po/main.py
python_gpt_po/models/__init__.py
python_gpt_po/models/config.py
python_gpt_po/models/enums.py
python_gpt_po/models/provider_clients.py
python_gpt_po/services/__init__.py
python_gpt_po/services/language_detector.py
python_gpt_po/services/model_manager.py
python_gpt_po/services/po_file_handler.py
python_gpt_po/services/translation_service.py
python_gpt_po/services/providers/__init__.py
python_gpt_po/services/providers/anthropic_provider.py
python_gpt_po/services/providers/azure_openai_provider.py
python_gpt_po/services/providers/base.py
python_gpt_po/services/providers/claude_sdk_provider.py
python_gpt_po/services/providers/deepseek_provider.py
python_gpt_po/services/providers/ollama_provider.py
python_gpt_po/services/providers/openai_provider.py
python_gpt_po/services/providers/provider_init.py
python_gpt_po/services/providers/registry.py
python_gpt_po/tests/test_ai_generated_tagging.py
python_gpt_po/tests/test_config_integration.py
python_gpt_po/tests/test_config_loader.py
python_gpt_po/tests/test_default_context.py
python_gpt_po/tests/test_django_compatibility.py
python_gpt_po/tests/test_django_special_codes.py
python_gpt_po/tests/test_duplicate_msgid.py
python_gpt_po/tests/test_english_fallback.py
python_gpt_po/tests/test_gitignore_functionality.py
python_gpt_po/tests/test_incremental_save.py
python_gpt_po/tests/test_language_detector.py
python_gpt_po/tests/test_locale_handling.py
python_gpt_po/tests/test_msgctxt_support.py
python_gpt_po/tests/test_multi_provider.py
python_gpt_po/tests/test_plural_handling.py
python_gpt_po/tests/test_po_translator.py
python_gpt_po/tests/test_skip_translated_files.py
python_gpt_po/tests/test_translation_detection.py
python_gpt_po/tests/test_whitespace_preservation.py
python_gpt_po/tests/integration/__init__.py
python_gpt_po/tests/integration/test_real_po_files.py
python_gpt_po/tests/providers/__init__.py
gpt_po_translator-2.0.1.dist-info/METADATA
gpt_po_translator-2.0.1.dist-info/WHEEL
gpt_po_translator-2.0.1.dist-info/entry_points.txt
gpt_po_translator-2.0.1.dist-info/top_level.txt
gpt_po_translator-2.0.1.dist-info/RECORD
