Metadata-Version: 2.4
Name: gpt-po-translator
Version: 2.0.1
Summary: A CLI tool for translating .po files using GPT models.
Author-email: Bram Mittendorff <bram@pescheck.io>
License: MIT
Classifier: Development Status :: 5 - Production/Stable
Classifier: Intended Audience :: Developers
Classifier: Intended Audience :: System Administrators
Classifier: Topic :: Software Development :: Internationalization
Classifier: Topic :: Software Development :: Localization
Classifier: Topic :: Text Processing :: Linguistic
Classifier: Operating System :: OS Independent
Classifier: Programming Language :: Python :: 3
Classifier: Programming Language :: Python :: 3.9
Classifier: Programming Language :: Python :: 3.10
Classifier: Programming Language :: Python :: 3.11
Classifier: Programming Language :: Python :: 3.12
Classifier: Programming Language :: Python :: 3.13
Classifier: Programming Language :: Python :: 3 :: Only
Classifier: Natural Language :: English
Classifier: Natural Language :: Dutch
Classifier: Environment :: Console
Classifier: Typing :: Typed
Requires-Python: >=3.9
License-File: LICENSE
Requires-Dist: polib==1.2.0
Requires-Dist: openai==1.99.9
Requires-Dist: python-dotenv==1.0.1
Requires-Dist: pytest==8.3.4
Requires-Dist: tenacity==9.0.0
Requires-Dist: setuptools-scm==8.1.0
Requires-Dist: pycountry==24.6.1
Requires-Dist: anthropic==0.63.0
Requires-Dist: requests==2.32.3
Requires-Dist: responses==0.25.8
Requires-Dist: isort==5.13.2
Requires-Dist: tomli==2.2.1
Requires-Dist: claude-agent-sdk>=0.1.0
Dynamic: license-file
